totd/__init__.py
totd/admin.py
totd/apps.py
totd/context_processors.py
totd/models.py
totd/tests.py
totd/views.py
totd/migrations/0001_Initial_models.py
totd/migrations/__init__.py
django_totd-1.0.2.dist-info/LICENSE
django_totd-1.0.2.dist-info/METADATA
django_totd-1.0.2.dist-info/WHEEL
django_totd-1.0.2.dist-info/top_level.txt
django_totd-1.0.2.dist-info/RECORD
