Metadata-Version: 2.1
Name: django-totd
Version: 1.0.2
Summary: Django app for adding a Tip of the Day to any page
Home-page: https://github.com/GetTogetherComm/totd
Author: Michael Hall
Author-email: mhall119@gmail.com
License: UNKNOWN
Platform: UNKNOWN
Classifier: Programming Language :: Python :: 3
Classifier: License :: OSI Approved :: BSD License
Classifier: Operating System :: OS Independent
Requires-Python: >=3.5
Requires-Dist: Django (>=2.2.0)
